aiosmbremote/__init__.py
aiosmbremote/__main__.py
aiosmbremote/_version.py
aiosmbremote/client.py
aiosmbremote/clienthandler.py
aiosmbremote/server.py
aiosmbremote/protocol/__init__.py
aiosmbremote/protocol/cmdtypes.py
aiosmbremote/protocol/common/__init__.py
aiosmbremote/protocol/common/cmdcontinue.py
aiosmbremote/protocol/common/cmderr.py
aiosmbremote/protocol/common/cmdlog.py
aiosmbremote/protocol/common/cmdok.py
aiosmbremote/protocol/common/cmdstop.py
aiosmbremote/protocol/connection/__init__.py
aiosmbremote/protocol/connection/cmdconnect.py
aiosmbremote/protocol/connection/cmdconnection.py
aiosmbremote/protocol/connection/cmddisconnect.py
aiosmbremote/protocol/connection/cmdwebconnect.py
aiosmbremote/protocol/dcsync/__init__.py
aiosmbremote/protocol/dcsync/dcsync.py
aiosmbremote/protocol/dcsync/usersecret.py
aiosmbremote/protocol/filesystem/__init__.py
aiosmbremote/protocol/filesystem/cmdcreateentry.py
aiosmbremote/protocol/filesystem/cmddelentry.py
aiosmbremote/protocol/filesystem/cmdfiledata.py
aiosmbremote/protocol/filesystem/cmdfsentry.py
aiosmbremote/protocol/filesystem/cmdgetfiledata.py
aiosmbremote/protocol/filesystem/cmdgetfsentrysd.py
aiosmbremote/protocol/filesystem/cmdlistdirectory.py
aiosmbremote/protocol/filesystem/cmdlistshares.py
aiosmbremote/protocol/filesystem/cmdshare.py
aiosmbremote/protocol/filesystem/fsentrysd.py
aiosmbremote/protocol/ioctl/__init__.py
aiosmbremote/protocol/ioctl/interfaceenty.py
aiosmbremote/protocol/ioctl/listinterfaces.py
aiosmbremote/protocol/secretsdump/__init__.py
aiosmbremote/protocol/secretsdump/lsass.py
aiosmbremote/protocol/secretsdump/lsasssecret.py
aiosmbremote/protocol/secretsdump/registry.py
aiosmbremote/protocol/secretsdump/regsecret.py
aiosmbremote/protocol/servicemanager/__init__.py
aiosmbremote/protocol/servicemanager/controlservice.py
aiosmbremote/protocol/servicemanager/createservice.py
aiosmbremote/protocol/servicemanager/listservices.py
aiosmbremote/protocol/servicemanager/serviceentry.py
aiosmbremote-0.0.6.dist-info/METADATA
aiosmbremote-0.0.6.dist-info/WHEEL
aiosmbremote-0.0.6.dist-info/entry_points.txt
aiosmbremote-0.0.6.dist-info/top_level.txt
aiosmbremote-0.0.6.dist-info/RECORD
